mleko/__init__.py
mleko/cache/__init__.py
mleko/cache/cache_mixin.py
mleko/cache/fingerprinters/__init__.py
mleko/cache/fingerprinters/base_fingerprinter.py
mleko/cache/fingerprinters/callable_source_fingerprinter.py
mleko/cache/fingerprinters/csv_fingerprinter.py
mleko/cache/fingerprinters/json_fingerprinter.py
mleko/cache/fingerprinters/optuna_pruner_fingerprinter.py
mleko/cache/fingerprinters/optuna_sampler_fingerprinter.py
mleko/cache/fingerprinters/vaex_fingerprinter.py
mleko/cache/handlers/__init__.py
mleko/cache/handlers/base_cache_handler.py
mleko/cache/handlers/joblib_cache_handler.py
mleko/cache/handlers/json_cache_handler.py
mleko/cache/handlers/pickle_cache_handler.py
mleko/cache/handlers/string_cache_handler.py
mleko/cache/handlers/vaex_cache_handler.py
mleko/cache/lru_cache_mixin.py
mleko/dataset/__init__.py
mleko/dataset/convert/__init__.py
mleko/dataset/convert/base_converter.py
mleko/dataset/convert/csv_to_vaex_converter.py
mleko/dataset/data_schema.py
mleko/dataset/export/__init__.py
mleko/dataset/export/base_exporter.py
mleko/dataset/export/local_exporter.py
mleko/dataset/export/s3_exporter.py
mleko/dataset/feature_select/__init__.py
mleko/dataset/feature_select/base_feature_selector.py
mleko/dataset/feature_select/composite_feature_selector.py
mleko/dataset/feature_select/invariance_feature_selector.py
mleko/dataset/feature_select/missing_rate_feature_selector.py
mleko/dataset/feature_select/pearson_correlation_feature_selector.py
mleko/dataset/feature_select/variance_feature_selector.py
mleko/dataset/filter/__init__.py
mleko/dataset/filter/base_filter.py
mleko/dataset/filter/expression_filter.py
mleko/dataset/filter/imblearn_resampling_filter.py
mleko/dataset/ingest/__init__.py
mleko/dataset/ingest/base_ingester.py
mleko/dataset/ingest/kaggle_ingester.py
mleko/dataset/ingest/s3_ingester.py
mleko/dataset/split/__init__.py
mleko/dataset/split/base_splitter.py
mleko/dataset/split/expression_splitter.py
mleko/dataset/split/random_splitter.py
mleko-4.3.0.dist-info/LICENSE
mleko-4.3.0.dist-info/METADATA
mleko-4.3.0.dist-info/WHEEL
mleko-4.3.0.dist-info/RECORD
