Metadata-Version: 2.1
Name: mleko
Version: 4.3.0
Summary: ML-Ekosystem
Home-page: https://github.com/klarna-incubator/mleko
License: Apache-2.0
Author: Erik Båvenstrand
Author-email: erik@bavenstrand.se
Requires-Python: >=3.8.1,<3.11.dev0
Classifier: Development Status :: 4 - Beta
Classifier: License :: OSI Approved :: Apache Software License
Classifier: Programming Language :: Python :: 3
Classifier: Programming Language :: Python :: 3.9
Classifier: Programming Language :: Python :: 3.10
Classifier: Programming Language :: Python :: 3.8
Requires-Dist: boto3 (>=1.26.91,<2.0.0)
Requires-Dist: botocore (>=1.29.91,<2.0.0)
Requires-Dist: imbalanced-learn (>=0.12.0,<0.13.0)
Requires-Dist: joblib (>=1.3.1,<2.0.0)
Requires-Dist: lightgbm (>=4.0.0,<5.0.0)
Requires-Dist: optuna (>=3.3.0,<4.0.0)
Requires-Dist: optuna-dashboard (>=0.14.0,<0.15.0)
Requires-Dist: pandas (>=2.0.3,<3.0.0)
Requires-Dist: scikit-learn (>=1.2.2,<2.0.0)
Requires-Dist: tqdm (>=4.65.0,<5.0.0)
Requires-Dist: urllib3 (>=1.25.4,<1.27)
Requires-Dist: vaex (>=4.16.0,<5.0.0)
Project-URL: Changelog, https://github.com/klarna-incubator/mleko/blob/main/CHANGELOG.md
Project-URL: Documentation, https://mleko.readthedocs.io
Project-URL: Repository, https://github.com/klarna-incubator/mleko
